dml_ui/__about__.py
dml_ui/__init__.py
dml_ui/cloudwatch.py
dml_ui/impl.py
dml_ui/plugin_examples.py
dml_ui/plugins.py
dml_ui/util.py
dml_ui/static/cutebot-eating-dags.gif
dml_ui/static/cutebot-explosion.webp
dml_ui/static/cutebot-inthecity.webp
dml_ui/static/cutebot-underwater.webp
dml_ui/static/cutebot.webp
dml_ui/static/devil-ride.webp
dml_ui/templates/404.html
dml_ui/templates/commit.html
dml_ui/templates/dag.html
dml_ui/templates/index.html
dml_ui/templates/indexes.html
dml_ui/templates/layout.html
dml_ui/templates/nav-dropdown.html
dml_ui/templates/node.html
dml_ui/templates/repo.html
dml_ui-0.0.6.dist-info/METADATA
dml_ui-0.0.6.dist-info/WHEEL
dml_ui-0.0.6.dist-info/entry_points.txt
dml_ui-0.0.6.dist-info/licenses/LICENSE.txt
dml_ui-0.0.6.dist-info/RECORD
